dynamic_initial_data/__init__.py
dynamic_initial_data/apps.py
dynamic_initial_data/base.py
dynamic_initial_data/exceptions.py
dynamic_initial_data/models.py
dynamic_initial_data/urls.py
dynamic_initial_data/version.py
dynamic_initial_data/management/__init__.py
dynamic_initial_data/management/commands/__init__.py
dynamic_initial_data/management/commands/update_initial_data.py
dynamic_initial_data/migrations/0001_initial.py
dynamic_initial_data/migrations/__init__.py
dynamic_initial_data/tests/__init__.py
dynamic_initial_data/tests/base_tests.py
dynamic_initial_data/tests/integration_tests.py
dynamic_initial_data/tests/management_command_tests.py
dynamic_initial_data/tests/mocks.py
dynamic_initial_data/tests/models.py
dynamic_initial_data/tests/fake_app_1/__init__.py
dynamic_initial_data/tests/fake_app_2/__init__.py
dynamic_initial_data/tests/fake_app_2/fixtures/__init__.py
dynamic_initial_data/tests/fake_app_2/fixtures/initial_data.py
dynamic_initial_data/tests/migrations/0001_initial.py
dynamic_initial_data/tests/migrations/__init__.py
django_dynamic_initial_data-2.2.1.dist-info/LICENSE
django_dynamic_initial_data-2.2.1.dist-info/METADATA
django_dynamic_initial_data-2.2.1.dist-info/WHEEL
django_dynamic_initial_data-2.2.1.dist-info/top_level.txt
django_dynamic_initial_data-2.2.1.dist-info/RECORD
