Metadata-Version: 2.1
Name: django-dynamic-initial-data
Version: 2.2.1
Summary: Dynamic initial data fixtures for Django apps
Home-page: https://github.com/ambitioninc/django-dynamic-initial-data
Author: 
Author-email: opensource@ambition.com
License: MIT
Keywords: Django fixtures
Classifier: Programming Language :: Python
Classifier: Programming Language :: Python :: 3.7
Classifier: Programming Language :: Python :: 3.8
Classifier: Programming Language :: Python :: 3.9
Classifier: Intended Audience :: Developers
Classifier: License :: OSI Approved :: MIT License
Classifier: Operating System :: OS Independent
Classifier: Framework :: Django
Classifier: Framework :: Django :: 3.2
Classifier: Framework :: Django :: 4.0
Classifier: Framework :: Django :: 4.1
Classifier: Framework :: Django :: 4.2
License-File: LICENSE
Requires-Dist: Django (>=3.2)
Requires-Dist: django-manager-utils (>=3.1.0)
